CS220/Lab3/t_flipflop.v
module t_flipflop(
    q, q_bar,
    toggle, clk, rst
);

    input toggle, clk, rst;
    output reg q, q_bar;

    initial begin
        q = 0;
        q_bar = 1;
    end

    always@(negedge clk or posedge rst) begin // needs a negedge here
        if (rst) begin
            q = 0;
        end else begin
            case(toggle)
                1'b0:
                    q = q;

                1'b1:
                    q = q_bar;
            endcase
        end
        q_bar = ~q;
    end 


endmodule

CS220/Lab3/mod_10_asynchronous_counter.v
`include "t_flipflop.v"

module mod_10_asynchronous_counter(
    output [3:0] q,
    input clk,
    input rst
);
    wire reset;
    reg RESET;
    always @(rst or reset) begin
        RESET <= rst | reset;
    end
    check_for_number check(.q(q), .reset(reset));
    t_flipflop ff0(.rst(RESET), .q(q[0]), .toggle(1'b1), .clk(clk));
    t_flipflop ff1(.rst(RESET), .q(q[1]), .toggle(1'b1), .clk(q[0]));
    t_flipflop ff2(.rst(RESET), .q(q[2]), .toggle(1'b1), .clk(q[1]));
    t_flipflop ff3(.rst(RESET), .q(q[3]), .toggle(1'b1), .clk(q[2]));

endmodule

module check_for_number(
    output reg reset,
    input [3:0] q
);

    always @(*) begin
        if (q == 4'b1010) reset <= 1'b1;
        else reset <= 1'b0;
    end

endmodule

CS220/Lab3/mod_10_asynchronous_counter_tb.v
`include "mod_10_asynchronous_counter.v"
`timescale 1ms/1ps

module mod_10_asynchronous_counter_tb();

    wire [3:0] q;
    reg rst;
    reg clk;
    integer i;
    mod_10_asynchronous_counter counter(.q(q), .rst(rst), .clk(clk));

    initial begin
        $dumpfile("vcd/mod_10_asynchronous_counter_tb.vcd");
        $dumpvars(5, mod_10_asynchronous_counter_tb);
        #85
        rst = 0;
        #15;
        rst = 0;
        #40
        $finish;
	end

    initial begin
        $monitor("%b \t %b", rst, q);
    end

	initial begin
		clk = 0;
		for(i = 0; i < 140; i = i + 1)
			#2 clk = ~clk;
	end

endmodule

CS220/Lab3/vcd/mod_10_asynchronous_counter_tb.vcd
$date
	Wed Feb 15 19:59:23 2023
$end
$version
	Icarus Verilog
$end
$timescale
	1ps
$end
$scope module mod_10_asynchronous_counter_tb $end
$var wire 4 ! q [3:0] $end
$var reg 1 " clk $end
$var reg 1 # rst $end
$var integer 32 $ i [31:0] $end
$scope module counter $end
$var wire 1 " clk $end
$var wire 1 # rst $end
$var wire 1 % reset $end
$var wire 4 & q [3:0] $end
$var reg 1 ' RESET $end
$scope module check $end
$var wire 4 ( q [3:0] $end
$var reg 1 % reset $end
$upscope $end
$scope module ff0 $end
$var wire 1 " clk $end
$var wire 1 ' rst $end
$var wire 1 ) toggle $end
$var reg 1 * q $end
$var reg 1 + q_bar $end
$upscope $end
$scope module ff1 $end
$var wire 1 , clk $end
$var wire 1 ' rst $end
$var wire 1 - toggle $end
$var reg 1 . q $end
$var reg 1 / q_bar $end
$upscope $end
$scope module ff2 $end
$var wire 1 0 clk $end
$var wire 1 ' rst $end
$var wire 1 1 toggle $end
$var reg 1 2 q $end
$var reg 1 3 q_bar $end
$upscope $end
$scope module ff3 $end
$var wire 1 4 clk $end
$var wire 1 ' rst $end
$var wire 1 5 toggle $end
$var reg 1 6 q $end
$var reg 1 7 q_bar $end
$upscope $end
$upscope $end
$upscope $end
$enddefinitions $end
#0
$dumpvars
07
16
15
14
03
12
11
10
0/
1.
1-
1,
0+
1*
1)
b1111 (
x'
b1111 &
0%
b0 $
x#
0"
b1111 !
$end
#2000000000
b1 $
1"
#4000000000
17
06
04
13
02
00
1/
0.
0,
1+
b0 !
b0 &
b0 (
0*
b10 $
0"
#6000000000
b11 $
1"
#8000000000
1,
0+
b1 !
b1 &
b1 (
1*
b100 $
0"
#10000000000
b101 $
1"
#12000000000
10
0/
1.
0,
1+
b10 !
b10 &
b10 (
0*
b110 $
0"
#14000000000
b111 $
1"
#16000000000
1,
0+
b11 !
b11 &
b11 (
1*
b1000 $
0"
#18000000000
b1001 $
1"
#20000000000
14
03
12
00
1/
0.
0,
1+
b100 !
b100 &
b100 (
0*
b1010 $
0"
#22000000000
b1011 $
1"
#24000000000
1,
0+
b101 !
b101 &
b101 (
1*
b1100 $
0"
#26000000000
b1101 $
1"
#28000000000
10
0/
1.
0,
1+
b110 !
b110 &
b110 (
0*
b1110 $
0"
#30000000000
b1111 $
1"
#32000000000
1,
0+
b111 !
b111 &
b111 (
1*
b10000 $
0"
#34000000000
b10001 $
1"
#36000000000
07
16
04
13
02
00
1/
0.
0,
1+
b1000 !
b1000 &
b1000 (
0*
b10010 $
0"
#38000000000
b10011 $
1"
#40000000000
1,
0+
b1001 !
b1001 &
b1001 (
1*
b10100 $
0"
#42000000000
b10101 $
1"
#44000000000
17
06
x'
0%
00
1/
0.
0,
1+
b0 !
b0 &
b0 (
0*
b10110 $
0"
#46000000000
b10111 $
1"
#48000000000
1,
0+
b1 !
b1 &
b1 (
1*
b11000 $
0"
#50000000000
b11001 $
1"
#52000000000
10
0/
1.
0,
1+
b10 !
b10 &
b10 (
0*
b11010 $
0"
#54000000000
b11011 $
1"
#56000000000
1,
0+
b11 !
b11 &
b11 (
1*
b11100 $
0"
#58000000000
b11101 $
1"
#60000000000
14
03
12
00
1/
0.
0,
1+
b100 !
b100 &
b100 (
0*
b11110 $
0"
#62000000000
b11111 $
1"
#64000000000
1,
0+
b101 !
b101 &
b101 (
1*
b100000 $
0"
#66000000000
b100001 $
1"
#68000000000
10
0/
1.
0,
1+
b110 !
b110 &
b110 (
0*
b100010 $
0"
#70000000000
b100011 $
1"
#72000000000
1,
0+
b111 !
b111 &
b111 (
1*
b100100 $
0"
#74000000000
b100101 $
1"
#76000000000
07
16
04
13
02
00
1/
0.
0,
1+
b1000 !
b1000 &
b1000 (
0*
b100110 $
0"
#78000000000
b100111 $
1"
#80000000000
1,
0+
b1001 !
b1001 &
b1001 (
1*
b101000 $
0"
#82000000000
b101001 $
1"
#84000000000
17
06
x'
0%
00
1/
0.
0,
1+
b0 !
b0 &
b0 (
0*
b101010 $
0"
#85000000000
0'
0#
#86000000000
b101011 $
1"
#88000000000
1,
0+
b1 !
b1 &
b1 (
1*
b101100 $
0"
#90000000000
b101101 $
1"
#92000000000
10
0/
1.
0,
1+
b10 !
b10 &
b10 (
0*
b101110 $
0"
#94000000000
b101111 $
1"
#96000000000
1,
0+
b11 !
b11 &
b11 (
1*
b110000 $
0"
#98000000000
b110001 $
1"
#100000000000
14
03
12
00
1/
0.
0,
1+
b100 !
b100 &
b100 (
0*
b110010 $
0"
#102000000000
b110011 $
1"
#104000000000
1,
0+
b101 !
b101 &
b101 (
1*
b110100 $
0"
#106000000000
b110101 $
1"
#108000000000
10
0/
1.
0,
1+
b110 !
b110 &
b110 (
0*
b110110 $
0"
#110000000000
b110111 $
1"
#112000000000
1,
0+
b111 !
b111 &
b111 (
1*
b111000 $
0"
#114000000000
b111001 $
1"
#116000000000
07
16
04
13
02
00
1/
0.
0,
1+
b1000 !
b1000 &
b1000 (
0*
b111010 $
0"
#118000000000
b111011 $
1"
#120000000000
1,
0+
b1001 !
b1001 &
b1001 (
1*
b111100 $
0"
#122000000000
b111101 $
1"
#124000000000
17
06
0'
0%
00
1/
0.
0,
1+
b0 !
b0 &
b0 (
0*
b111110 $
0"
#126000000000
b111111 $
1"
#128000000000
1,
0+
b1 !
b1 &
b1 (
1*
b1000000 $
0"
#130000000000
b1000001 $
1"
#132000000000
10
0/
1.
0,
1+
b10 !
b10 &
b10 (
0*
b1000010 $
0"
#134000000000
b1000011 $
1"
#136000000000
1,
0+
b11 !
b11 &
b11 (
1*
b1000100 $
0"
#138000000000
b1000101 $
1"
#140000000000
14
03
12
00
1/
0.
0,
1+
b100 !
b100 &
b100 (
0*
b1000110 $
0"
