CS220/Lab3/moore_sequence_detector.v
`timescale 1ns / 1ps

module moore_sequence_detector(
input in, clk, reset,
output reg out
);

parameter S0 = 0 , S1 = 1 , S2 = 2 , S3 = 3 , S4 = 4;
reg [2:0] PS, NS;

always @(posedge clk, posedge reset) begin
    if(reset)
        PS <= S0;   
    else    
        PS <= NS ; 
end

always @(PS, in) begin          // you need to update next state on the basis of new present state
    case(PS)
        S0 : begin
                    NS = in ? S1 : S0;
                    $display(PS);
                end
        S1 : begin 
                    NS = in ? S1 : S2;
                    $display(PS);
                end
        S2 : begin 
                    NS = in ? S3 : S0;
                    $display(PS);
                end 
        S3 : begin 
                    NS = in ? S1 : S4;
                    $display(PS);
                end
        S4 : begin 
                    NS = in ? S3 : S0;
                    $display(PS);
                end
        default: NS = S0; 
    endcase
end

always @(PS) begin
  case(PS)
    S4: out = 1;
    default: out = 0;
  endcase 
end 

endmodule

CS220/Lab3/moore_sequence_detector_tb.v
`include "moore_sequence_detector.v"
`timescale 1ns / 1ps

 module moore_sequence_detector_tb();
    // Inputs
    reg in;
    reg clk;
    reg reset;
    // Outputs
    wire out;
    // Instantiate the Unit Under Test (UUT)
    moore_sequence_detector uut (
        .in(in), 
        .clk(clk), 
        .reset(reset), 
        .out(out)
    );

    always #5 clk = ~ clk;  

    initial begin
        $dumpfile("vcd/moore_sequence_detector_tb.vcd");
        $dumpvars(3, moore_sequence_detector_tb);
        // fork                                             // what does fork do
        clk = 1'b0;
        reset = 1'b0;
        // begin 
        in = 1; #10 in = 0; #10 in = 1; #10 in = 0;
        // #10 in = 1; #10 in = 0; #10 in = 1; #10 in = 0;  //! misbehavior
        #10 in = 1; #10 in = 0; #10 in = 1; #10 in = 0;
        #10 in = 1; #10 in = 0; #10 in = 0; #10 in = 1;
        #10 in = 0; #10 in = 1; #10 in = 1; #10 in = 0;
        #10 
        $finish;
        // end
        // join  
    end 

    initial begin
        $monitor("%b %b \t %b", reset, in, out);
        reset = 1'b1;
        #5 reset = 1'b0;
    end
endmodule

CS220/Lab3/vcd/moore_sequence_detector_tb.vcd
$date
	Wed Feb 15 17:52:31 2023
$end
$version
	Icarus Verilog
$end
$timescale
	1ps
$end
$scope module moore_sequence_detector_tb $end
$var wire 1 ! out $end
$var reg 1 " clk $end
$var reg 1 # in $end
$var reg 1 $ reset $end
$scope module uut $end
$var wire 1 " clk $end
$var wire 1 # in $end
$var wire 1 $ reset $end
$var reg 3 % NS [2:0] $end
$var reg 3 & PS [2:0] $end
$var reg 1 ! out $end
$upscope $end
$upscope $end
$enddefinitions $end
#0
$dumpvars
b0 &
b1 %
1$
1#
0"
0!
$end
#5000
b1 &
0$
1"
#10000
b10 %
0"
0#
#15000
b0 %
b10 &
1"
#20000
b11 %
0"
1#
#25000
b1 %
b11 &
1"
#30000
b100 %
0"
0#
#35000
1!
b0 %
b100 &
1"
#40000
b11 %
0"
1#
#45000
0!
b1 %
b11 &
1"
#50000
b100 %
0"
0#
#55000
1!
b0 %
b100 &
1"
#60000
b11 %
0"
1#
#65000
0!
b1 %
b11 &
1"
#70000
b100 %
0"
0#
#75000
1!
b0 %
b100 &
1"
#80000
b11 %
0"
1#
#85000
0!
b1 %
b11 &
1"
#90000
b100 %
0"
0#
#95000
1!
b0 %
b100 &
1"
#100000
0"
#105000
0!
b0 &
1"
#110000
b1 %
0"
1#
#115000
b1 &
1"
#120000
b10 %
0"
0#
#125000
b0 %
b10 &
1"
#130000
b11 %
0"
1#
#135000
b1 %
b11 &
1"
#140000
0"
#145000
b1 &
1"
#150000
b10 %
0"
0#
#155000
b0 %
b10 &
1"
