CS220/extras/FSMCode/CS220_Lecture10_FSMCode/fsm_using_always.v
//-----------------------------------------------------
// This is FSM demo program using always block
// Design Name : fsm_using_always
// File Name   : fsm_using_always.v
//-----------------------------------------------------
module fsm_using_always (
clock      , // clock
reset      , // Active high, syn reset
req_0      , // Request 0
req_1      , // Request 1
gnt_0      , // Grant 0
gnt_1
);
//-------------Input Ports-----------------------------
input   clock,reset,req_0,req_1;
 //-------------Output Ports----------------------------
output  gnt_0,gnt_1;
//-------------Input ports Data Type-------------------
wire    clock,reset,req_0,req_1;
//-------------Output Ports Data Type------------------
reg     gnt_0,gnt_1;
//-------------Internal Constants--------------------------
parameter SIZE = 3           ;
parameter IDLE  = 3'b001,GNT0 = 3'b010,GNT1 = 3'b100 ;
//-------------Internal Variables---------------------------
reg   [SIZE-1:0]          state        ;// Seq part of the FSM
reg   [SIZE-1:0]          next_state   ;// combo part of FSM
//----------Code startes Here------------------------
always @ (state or req_0 or req_1)
begin : FSM_COMBO
 //next_state = 3'b000;
 case(state)
   IDLE : if (req_0 == 1'b1) begin
                next_state <= GNT0;
              end else if (req_1 == 1'b1) begin
                next_state <= GNT1;
              end else begin
                next_state <= IDLE;
              end
   GNT0 : if (req_0 == 1'b1) begin
                next_state <= GNT0;
          end
          else if (req_1== 1'b1) begin
            next_state <= GNT1;
          end
          else begin
            next_state <= IDLE;
          end
   GNT1 : if (req_1 == 1'b1) begin
                next_state <= GNT1;
              end
              else if (req_0== 1'b1) begin
                next_state <= GNT0;
              end
              else begin
                next_state <= IDLE;
              end
   default : next_state <= IDLE;
  endcase
end
//----------Seq Logic-----------------------------
always @ (posedge clock)
begin : FSM_SEQ
  if (reset == 1'b1) begin
    state <=  IDLE;
  end else begin
    state <=  next_state;
  end
end
//----------Output Logic-----------------------------
always @ (posedge clock)
begin : OUTPUT_LOGIC
if (reset == 1'b1) begin
  gnt_0 <=  1'b0;
  gnt_1 <=  1'b0;
end
else begin
  case(state)
    IDLE : begin
                  gnt_0 <=  1'b0;
                  gnt_1 <=  1'b0;
               end
   GNT0 : begin
                   gnt_0 <=  1'b1;
                   gnt_1 <=  1'b0;
                end
   GNT1 : begin
                   gnt_0 <=  1'b0;
                   gnt_1 <=  1'b1;
                end
   default : begin
                    gnt_0 <=  1'b0;
                    gnt_1 <=  1'b0;
                  end
  endcase
end
end // End Of Block OUTPUT_LOGIC

endmodule // End of Module arbiter

CS220/extras/FSMCode/CS220_Lecture10_FSMCode/fsm_using_always_tb.v
`include "fsm_using_always.v"

module fsm_using_always_tb;
// Inputs
reg clock,reset,req_0,req_1;
wire [2:0] state;
// Outputs
wire gnt_0,gnt_1;

// Instantiate the Unit Under Test (UUT)
fsm_using_always m1(clock,reset,req_0,req_1,gnt_0,gnt_1);

always #1 clock=~clock;
initial
    begin
    $dumpfile("fsm_using_always.vcd");
    $dumpvars(0,fsm_using_always_tb);
        clock=1;
        #10;
        reset=1'b1;
        //state=3'b001;//idle
        req_0=1'b0;
        req_1=1'b0;
        #10;
        reset=1'b0;
        #10
      //  state=3'b001;
        req_0=1'b1;
        req_1=1'b0;
        #10;
        reset=1'b0;
      //  state=3'b010;
        req_0=1'b0;
        req_1=1'b0;
        #10;
        reset=1'b0;
      //  state=3'b001;
        req_0=1'b0;
        req_1=1'b1;
        #10;
        reset=1'b0;
      //  state=3'b100;
        req_0=1'b0;
        req_1=1'b0;
        #10;
        reset=1'b0;
    //    state=3'b001;
        req_0=1'b1;
        req_1=1'b1;
        #10;

        $finish;
    end
endmodule

CS220/extras/FSMCode/CS220_Lecture10_FSMCode/fsm_using_always.vcd
$date
	Sun Feb  5 16:06:22 2023
$end
$version
	Icarus Verilog
$end
$timescale
	1s
$end
$scope module fsm_using_always_tb $end
$var wire 1 ! gnt_1 $end
$var wire 1 " gnt_0 $end
$var reg 1 # clock $end
$var reg 1 $ req_0 $end
$var reg 1 % req_1 $end
$var reg 1 & reset $end
$scope module m1 $end
$var wire 1 # clock $end
$var wire 1 $ req_0 $end
$var wire 1 % req_1 $end
$var wire 1 & reset $end
$var reg 1 " gnt_0 $end
$var reg 1 ! gnt_1 $end
$var reg 3 ' next_state [2:0] $end
$var reg 3 ( state [2:0] $end
$scope begin FSM_COMBO $end
$upscope $end
$scope begin FSM_SEQ $end
$upscope $end
$scope begin OUTPUT_LOGIC $end
$upscope $end
$upscope $end
$upscope $end
$enddefinitions $end
#0
$dumpvars
bx (
bx '
x&
x%
x$
1#
0"
0!
$end
#1
0#
#2
1#
#3
0#
#4
1#
#5
0#
#6
1#
#7
0#
#8
1#
#9
0#
#10
b1 (
b1 '
1#
0%
0$
1&
#11
0#
#12
1#
#13
0#
#14
1#
#15
0#
#16
1#
#17
0#
#18
1#
#19
0#
#20
1#
0&
#21
0#
#22
1#
#23
0#
#24
1#
#25
0#
#26
1#
#27
0#
#28
1#
#29
0#
#30
b10 '
1#
1$
#31
0#
#32
b10 (
1#
#33
0#
#34
1"
1#
#35
0#
#36
1#
#37
0#
#38
1#
#39
0#
#40
b1 '
1#
0$
#41
0#
#42
b1 (
1#
#43
0#
#44
0"
1#
#45
0#
#46
1#
#47
0#
#48
1#
#49
0#
#50
b100 '
1#
1%
#51
0#
#52
b100 (
1#
#53
0#
#54
1!
1#
#55
0#
#56
1#
#57
0#
#58
1#
#59
0#
#60
b1 '
1#
0%
#61
0#
#62
b1 (
1#
#63
0#
#64
0!
1#
#65
0#
#66
1#
#67
0#
#68
1#
#69
0#
#70
b10 '
1#
1%
1$
#71
0#
#72
b10 (
1#
#73
0#
#74
1"
1#
