CS220/Lab5/floating_point_addition.v
module floating_point_addition(
    input [size-1:0] a,
    input [size-1:0] b,
    input reset,
    input clk,
    output reg [size-1:0] C,
    output reg corrupt,
    output reg done
);

    parameter size = 32;
    parameter exp_base = 23;
    parameter   Ssave = 0, 
                Scompare = 1, 
                SsaveMantissa = 2, 
                Sshift = 3, 
                SadjustMagnitude = 4, 
                Sadd = 5, 
                SbackToC = 6, 
                SinvertMantissaC = 7, 
                SnormalizeC = 8,
                SmantissaBackToC = 9, 
                Sstay = 10;

    // Intermediate variables
    reg [size-1:0] A, B;
    reg [exp_base+2:0] signed_a, signed_b, signed_c;
    reg [3:0] mode, next_mode;

    // update state
    always @(posedge clk, reset) begin
        if(reset) begin
            mode <= Ssave;
            done <= 1'b0;
        end
        else if(done)
            mode <= Sstay;
        else
            mode <= next_mode; 
    end

    always @(mode, clk) begin
        next_mode <= Ssave; // initialises the FSM
        case(mode)

            Ssave: begin
                /**
                Save A and B in intermediate registers for operation
                Exchange A and B if B > A
                */
                A <= a;
                B <= b;
                // $display("[DBG] save:");
                next_mode <= Scompare;
            end

            Scompare: begin
                if (A[size-2:exp_base] < B[size-2:exp_base]) begin
                    // lesser exponent A
                    A <= B;
                    B <= A;
                end
                // $display("[DBG] compare:");
                next_mode <= SsaveMantissa;
            end

            SsaveMantissa: begin
                // 0 0 1 . mantissa
                // ^ ^ ^
                // | | - hidden 1 at start
                // | - for magnitude not to overflow
                // - for sign
                // at the below start, signed_a, signed_b just store the magnitudes of A, B mantissas
                signed_a <= {1'b0, {1'b0, {1'b1, A[exp_base-1:0]}}};    
                signed_b <= {1'b0, {1'b0, {1'b1, B[exp_base-1:0]}}};
                // $display("[DBG] saveMantissa: A=%b %b, B=%b %b", A[size-1], {1'b1, A[exp_base-1:0]}, B[size-1], {1'b1, B[exp_base-1:0]});
                // $display("[DBG] saveMantissa: signed_a=%b, signed_b=%b", signed_a, signed_b);
                next_mode <= Sshift;
            end

            Sshift: begin
                /**
                Shift register B left until exponent matches
                */
                if (A[size-2:exp_base] > B[size-2:exp_base]) begin
                    signed_b[exp_base:0] <= signed_b[exp_base:0] >> 1;
                    B[size-2:exp_base] <= B[size-2:exp_base] + 1;
                    // $display("[DBG] shift: shifted signed_b to %b", signed_b[exp_base-1:0]);
                    next_mode <= Sshift;                                    
                end else begin
                    // $display("[DBG] shift: exponent final value %b", B[size-2:exp_base]);
                    next_mode <= SadjustMagnitude;
                end
            end

            SadjustMagnitude: begin
                //! let the following happen only once
                if (A[size-1] == 1'b1) begin
                    signed_a <= ~signed_a + 1;
                    // $display("[DBG] adjustMagnitude: set inverted magnitude A");
                end
                if (B[size-1] == 1'b1) begin
                    signed_b <= ~signed_b + 1;
                    // $display("[DBG] adjustMagnitude: set inverted magnitude B");
                end
                next_mode <= Sadd;
            end

            Sadd: begin
                /**
                now exponents should match
                put them together
                */
                signed_c <= signed_a + signed_b;                    // this would lead to dropping of Cout
                // $display("signed_a=%b", signed_a);
                // $display("signed_b=%b", signed_b);
                // $display("signed_c=%b", signed_c);
                next_mode <= SbackToC;
            end

            SbackToC: begin
                C[size-1] <= signed_c[exp_base+2];                  // assign sign as the MSB
                C[size-2:exp_base] <= A[size-2:exp_base];           // assign exponent of any number
                // $display("[DBG] backToC: C=%b", C);
                next_mode <= SinvertMantissaC;
            end

            SinvertMantissaC: begin                                 // store the magnitude
                if (signed_c[exp_base+2] == 1'b1) begin
                    signed_c[exp_base+1:0] <= ~signed_c[exp_base+1:0] + 1; // signed_a storing intermediate 2's complement
                    // $display("[DBG] invertMantissaC: Inverting");
                end else begin
                    signed_c[exp_base+1:0] <= signed_c[exp_base+1:0];
                end
                next_mode <= SnormalizeC;
            end

            SnormalizeC: begin
                // ! running even when condition should be false
                if (signed_c[23+1] == 1'b1) begin
                    signed_c[exp_base+1:0] <= signed_c[exp_base+1:0] >> 1;
                    C[size-2:exp_base] <= C[size-2:exp_base] + 1;
                    // $display("[DBG] normalizeC: shift right signed_c=%b", signed_c);
                    next_mode <= next_mode;

                end else if (signed_c[exp_base] == 1'b0) begin                  // else shift right
                    signed_c[exp_base+1:0] <= signed_c[exp_base+1:0] << 1;
                    C[size-2:exp_base] <= C[size-2:exp_base] - 1;
                    // $display("[DBG] normalizeC: shift left signed_a=%b", signed_c);
                    next_mode <= next_mode;

                end else begin
                    C[exp_base-1:0] <= signed_c[exp_base-1:0];
                    // $display("[DBG] normalizeC: saved");
                    // $display("[DBG] normalizeC: signed_c=%b", signed_c);
                    next_mode <= SmantissaBackToC;
                end
            end

            SmantissaBackToC: begin
                C[exp_base-1:0] <= signed_c[exp_base-1:0];    
                next_mode <= Sstay;        
                done <= 1;
            end

            Sstay: begin
                // $display("[DBG] stay:");
                next_mode <= Sstay;
            end
            default: begin
                corrupt <= 1;
            end 
        endcase

    end

endmodule

CS220/Lab5/veda.v
module veda(
    input clk,
    input rst,
    input write_enable,
    input [4:0] addr,
    input [31:0] datain,
    input mode,
    output [31:0] dataout
);

    integer i;
    reg [31:0] cells[31:0]; // first signifies data bits, second is number of such cells
    reg [31:0] out;
    assign dataout = out;

    initial begin
        out <= 0;
        for (i = 0; i < 32; i = i + 1)
            cells[i] <= 0;
    end

    always @(posedge clk) begin
        if (rst == 1) begin

            for (i = 0; i < 32; i = i + 1) begin : reset
                cells[i] <= 0;
            end
            
        end else begin
            if (write_enable && mode == 0) begin : scribble

                cells[addr] <= datain;
                out <= datain;

            end else if (write_enable && mode == 1) begin : interpret

                cells[addr] <= datain;
                out <= cells[addr];
                
            end else begin

                out <= cells[addr];

            end
        end
    end

endmodule

CS220/Lab5/adder.v
`include "floating_point_addition.v"
`include "veda.v"

module adder(
    input clk,
    input reset,
    output reg flag
);
    reg write_enable;
    reg mode;
    reg [4:0] addr;
    reg [31:0] datain;
    wire [31:0] dataout;
    reg [31:0] A, B;
    wire [31:0] answer;
    wire corrupt, done;
    reg rst_;
    reg [3:0] counter;

    parameter Aval = 32'b01000011001010100100000000000000;
    parameter Bval = 32'b11000011011001011010000000000000;
    parameter Cval = 32'b11000010011011011000000000000000;

    parameter Aaddr = 5'b00001;
    parameter Baddr = 5'b00010;
    parameter Caddr = 5'b00011;

    veda storage(.clk(clk),
                 .rst(reset),
                 .write_enable(write_enable),
                 .addr(addr), 
                 .mode(mode), 
                 .datain(datain), 
                 .dataout(dataout));
    floating_point_addition add(.a(A), 
                                .b(B), 
                                .C(answer), 
                                .reset(rst_), 
                                .clk(clk), 
                                .corrupt(corrupt), 
                                .done(done));

    parameter S0 = 0, S1 = 1, S2 = 2, S3 = 3, S4 = 4, S5 = 5, Soff = 6;
    reg [3:0] PS, NS;
    always @(posedge clk, reset) begin
        if (reset) begin
            counter <= 0;
            rst_ <= 1;
            PS <= S0;
        end else begin
            rst_ <= 0;
            PS <= NS;
        end
    end

    always @(PS, posedge clk) begin
        NS <= S0;
        case (PS)
            S0: begin
                write_enable <= 1;
                addr <= Aaddr;
                datain <= Aval;
                mode <= 0;
                counter <= counter + 1;
                if (counter == 3) begin    // waiting till value has been set
                    NS <= S1;
                    counter <= 0;
                end
                else
                    NS <= S0;
            end
            S1: begin
                addr <= Baddr;
                datain <= Bval;
                mode <= 0;
                counter <= counter + 1;
                if (counter == 3) begin
                    NS <= Soff;
                    counter <= 0;
                end
                else
                    NS <= S1;
            end
            Soff: begin
                write_enable <= 0;
                NS <= S2;
            end
            S2: begin
                addr <= Aaddr;
                A <= dataout;
                counter <= counter + 1;
                if (counter == 3) begin
                    NS <= S3;
                    counter <= 0;
                end
                else
                    NS <= S2;
            end
            S3: begin
                addr <= Baddr;
                B <= dataout;
                counter <= counter + 1;
                if (counter == 3) begin
                    NS <= S4;
                    counter <= 0;
                end
                else
                    NS <= S3;
            end
            S4: begin
                rst_ <= 1;
                if (done) begin
                    write_enable <= 1;
                    addr = Caddr;
                    datain <= answer;
                    mode <= 0;
                    counter <= counter + 1;
                    if (counter == 3) begin
                        NS <= S5;
                        counter <= 0;
                    end else begin
                        NS <= S4;
                    end
                end else begin
                    NS <= S4;
                end
            end
            S5: begin
                if (answer == Cval) begin
                    flag <= 1'b1;
                end else begin
                    flag <= 1'b0;
                end
                NS <= S5;
            end
            default: begin
                NS <= S0;
            end
        endcase
    end

endmodule

CS220/Lab5/adder_tb.v
`include "adder.v"

module adder_tb();

    reg clk, reset;
    wire flag;

    adder a(.clk(clk), .reset(reset), .flag(flag));

    always #5 clk <= ~clk;

    initial begin
        $dumpfile("vcd/adder_tb.vcd");
        $dumpvars(5, adder_tb);
        clk <= 1'b0;
        reset <= 1'b0;
    end

    initial begin
        reset <= 1;
        #10
        reset <= 0;
        #500
        $finish;
    end

    initial begin
        $monitor("reset=%b, flag=%b", reset, flag);
    end

endmodule

CS220/Lab5/vcd/adder_tb.vcd
$date
	Thu Mar  2 15:23:03 2023
$end
$version
	Icarus Verilog
$end
$timescale
	1s
$end
$scope module adder_tb $end
$var wire 1 ! flag $end
$var reg 1 " clk $end
$var reg 1 # reset $end
$scope module a $end
$var wire 1 " clk $end
$var wire 1 # reset $end
$var wire 1 $ done $end
$var wire 32 % dataout [31:0] $end
$var wire 1 & corrupt $end
$var wire 32 ' answer [31:0] $end
$var reg 32 ( A [31:0] $end
$var reg 32 ) B [31:0] $end
$var reg 4 * NS [3:0] $end
$var reg 4 + PS [3:0] $end
$var reg 5 , addr [4:0] $end
$var reg 4 - counter [3:0] $end
$var reg 32 . datain [31:0] $end
$var reg 1 ! flag $end
$var reg 1 / mode $end
$var reg 1 0 rst_ $end
$var reg 1 1 write_enable $end
$scope module add $end
$var wire 32 2 a [31:0] $end
$var wire 32 3 b [31:0] $end
$var wire 1 " clk $end
$var wire 1 0 reset $end
$var reg 32 4 A [31:0] $end
$var reg 32 5 B [31:0] $end
$var reg 32 6 C [31:0] $end
$var reg 1 & corrupt $end
$var reg 1 $ done $end
$var reg 4 7 mode [3:0] $end
$var reg 4 8 next_mode [3:0] $end
$var reg 26 9 signed_a [25:0] $end
$var reg 26 : signed_b [25:0] $end
$var reg 26 ; signed_c [25:0] $end
$upscope $end
$scope module storage $end
$var wire 5 < addr [4:0] $end
$var wire 1 " clk $end
$var wire 32 = datain [31:0] $end
$var wire 32 > dataout [31:0] $end
$var wire 1 / mode $end
$var wire 1 # rst $end
$var wire 1 1 write_enable $end
$var reg 32 ? out [31:0] $end
$var integer 32 @ i [31:0] $end
$scope begin interpret $end
$upscope $end
$scope begin reset $end
$upscope $end
$scope begin scribble $end
$upscope $end
$upscope $end
$upscope $end
$upscope $end
$enddefinitions $end
#0
$dumpvars
b100000 @
b0 ?
b0 >
b1000011001010100100000000000000 =
b1 <
bx ;
bx :
bx 9
b1 8
b0 7
bx 6
bx 5
bx 4
bx 3
bx 2
11
10
0/
b1000011001010100100000000000000 .
b1 -
b1 ,
b0 +
b0 *
bx )
bx (
bx '
1&
b0 %
0$
1#
0"
x!
$end
#5
b1 8
b0 -
b100000 @
1"
#10
b1 7
b10 8
00
0"
0#
#15
b1xxxxxxxxxxxxxxxxxxxxxxx :
b1xxxxxxxxxxxxxxxxxxxxxxx 9
b11 8
b10 7
b1000011001010100100000000000000 %
b1000011001010100100000000000000 >
b1000011001010100100000000000000 ?
b1 -
1"
#20
b11 8
0"
#25
b100 8
b11 7
b10 -
1"
#30
b100 8
0"
#35
b101 8
b100 7
b11 -
1"
#40
b101 8
0"
#45
b110 8
b101 7
b1 *
b0 -
1"
#50
b110 8
0"
#55
b11000011011001011010000000000000 .
b11000011011001011010000000000000 =
b10 ,
b10 <
b111 8
b110 7
b1 +
b10 -
b1 *
1"
#60
b111 8
0"
#65
b1000 8
b111 7
b11000011011001011010000000000000 %
b11000011011001011010000000000000 >
b11000011011001011010000000000000 ?
b11 -
b1 *
1"
#70
b1000 8
0"
#75
b1001 8
b1000 7
b0 -
b110 *
1"
#80
b1001 8
0"
#85
1$
01
b1010 8
b1001 7
b110 +
b1 -
b10 *
1"
#90
b1010 8
0"
#95
b10 -
b11000011011001011010000000000000 (
b11000011011001011010000000000000 2
b1 ,
b1 <
b1010 8
b1010 7
b10 +
b10 *
1"
#100
b1010 8
0"
#105
b1010 8
b1000011001010100100000000000000 %
b1000011001010100100000000000000 >
b1000011001010100100000000000000 ?
b11 -
b10 *
1"
#110
b1010 8
0"
#115
b1010 8
b0 -
b1000011001010100100000000000000 (
b1000011001010100100000000000000 2
b11 *
1"
#120
b1010 8
0"
#125
b1000011001010100100000000000000 )
b1000011001010100100000000000000 3
b10 ,
b10 <
b1010 8
b11 +
b10 -
b11 *
1"
#130
b1010 8
0"
#135
b1010 8
b11000011011001011010000000000000 %
b11000011011001011010000000000000 >
b11000011011001011010000000000000 ?
b11 -
b11 *
1"
#140
b1010 8
0"
#145
b1010 8
b0 -
b11000011011001011010000000000000 )
b11000011011001011010000000000000 3
b100 *
1"
#150
b1010 8
0"
#155
b11000011011001011010000000000000 5
b1000011001010100100000000000000 4
0$
b0 7
bx .
bx =
11
10
b11 ,
b11 <
b1 8
b100 +
b10 -
b100 *
1"
#160
b1 8
0"
#165
b1 7
b10 8
bx %
bx >
bx ?
00
b100 *
1"
#170
b10 8
0"
#175
b111001011010000000000000 :
b101010100100000000000000 9
b11 8
b10 7
00
b100 *
1"
#180
b11 8
0"
#185
b100 8
b11 7
00
b100 *
1"
#190
b100 8
0"
#195
b11000110100110000000000000 :
b101 8
b100 7
00
b100 *
1"
#200
b111001011010000000000000 :
b101 8
0"
#205
b11110001001010000000000000 ;
b11000110100110000000000000 :
b110 8
b101 7
00
b100 *
1"
#210
b110 8
0"
#215
b110000110xxxxxxxxxxxxxxxxxxxxxxx '
b110000110xxxxxxxxxxxxxxxxxxxxxxx 6
b111 8
b110 7
00
b100 *
1"
#220
b111 8
0"
#225
b10001110110110000000000000 ;
b1000 8
b111 7
00
b100 *
1"
#230
b11110001001010000000000000 ;
b1000 8
0"
#235
b110000101xxxxxxxxxxxxxxxxxxxxxxx '
b110000101xxxxxxxxxxxxxxxxxxxxxxx 6
b10011101101100000000000000 ;
b1000 8
b1000 7
00
b100 *
1"
#240
b110000100xxxxxxxxxxxxxxxxxxxxxxx '
b110000100xxxxxxxxxxxxxxxxxxxxxxx 6
b10111011011000000000000000 ;
b1000 8
0"
#245
1$
b1001 7
b11000010011011011000000000000000 '
b11000010011011011000000000000000 6
b1010 8
00
b100 *
1"
#250
b1010 8
0"
#255
b1010 8
b1010 7
b11 -
b11000010011011011000000000000000 .
b11000010011011011000000000000000 =
00
b100 *
1"
#260
b1010 8
0"
#265
b1010 8
b11000010011011011000000000000000 %
b11000010011011011000000000000000 >
b11000010011011011000000000000000 ?
b0 -
00
b101 *
1"
#270
b1010 8
0"
#275
1!
b1010 8
b101 +
b1 -
00
b101 *
1"
#280
b1010 8
0"
#285
b1010 8
b101 *
1"
#290
b1010 8
0"
#295
b1010 8
b101 *
1"
#300
b1010 8
0"
#305
b1010 8
b101 *
1"
#310
b1010 8
0"
#315
b1010 8
b101 *
1"
#320
b1010 8
0"
#325
b1010 8
b101 *
1"
#330
b1010 8
0"
#335
b1010 8
b101 *
1"
#340
b1010 8
0"
#345
b1010 8
b101 *
1"
#350
b1010 8
0"
#355
b1010 8
b101 *
1"
#360
b1010 8
0"
#365
b1010 8
b101 *
1"
#370
b1010 8
0"
#375
b1010 8
b101 *
1"
#380
b1010 8
0"
#385
b1010 8
b101 *
1"
#390
b1010 8
0"
#395
b1010 8
b101 *
1"
#400
b1010 8
0"
#405
b1010 8
b101 *
1"
#410
b1010 8
0"
#415
b1010 8
b101 *
1"
#420
b1010 8
0"
#425
b1010 8
b101 *
1"
#430
b1010 8
0"
#435
b1010 8
b101 *
1"
#440
b1010 8
0"
#445
b1010 8
b101 *
1"
#450
b1010 8
0"
#455
b1010 8
b101 *
1"
#460
b1010 8
0"
#465
b1010 8
b101 *
1"
#470
b1010 8
0"
#475
b1010 8
b101 *
1"
#480
b1010 8
0"
#485
b1010 8
b101 *
1"
#490
b1010 8
0"
#495
b1010 8
b101 *
1"
#500
b1010 8
0"
#505
b1010 8
b101 *
1"
#510
b1010 8
0"
