CS220/Lab5/floating_point_addition.v
module floating_point_addition(
    input [size-1:0] a,
    input [size-1:0] b,
    input reset,
    input clk,
    output reg [size-1:0] C,
    output reg corrupt,
    output reg done
);

    parameter size = 32;
    parameter exp_base = 23;
    parameter   Ssave = 0, 
                Scompare = 1, 
                SsaveMantissa = 2, 
                Sshift = 3, 
                SadjustMagnitude = 4, 
                Sadd = 5, 
                SbackToC = 6, 
                SinvertMantissaC = 7, 
                SnormalizeC = 8,
                SmantissaBackToC = 9, 
                Sstay = 10;

    // Intermediate variables
    reg [size-1:0] A, B;
    reg [exp_base+2:0] signed_a, signed_b, signed_c;
    reg [3:0] mode, next_mode;

    // update state
    always @(posedge clk, reset) begin
        if(reset) begin
            mode <= Ssave;
            done <= 1'b0;
        end
        else if(done)
            mode <= Sstay;
        else
            mode <= next_mode; 
    end

    always @(mode, clk) begin
        next_mode <= Ssave; // initialises the FSM
        case(mode)

            Ssave: begin
                /**
                Save A and B in intermediate registers for operation
                Exchange A and B if B > A
                */
                A <= a;
                B <= b;
                // $display("[DBG] save:");
                next_mode <= Scompare;
            end

            Scompare: begin
                if (A[size-2:exp_base] < B[size-2:exp_base]) begin
                    // lesser exponent A
                    A <= B;
                    B <= A;
                end
                // $display("[DBG] compare:");
                next_mode <= SsaveMantissa;
            end

            SsaveMantissa: begin
                // 0 0 1 . mantissa
                // ^ ^ ^
                // | | - hidden 1 at start
                // | - for magnitude not to overflow
                // - for sign
                // at the below start, signed_a, signed_b just store the magnitudes of A, B mantissas
                signed_a <= {1'b0, {1'b0, {1'b1, A[exp_base-1:0]}}};    
                signed_b <= {1'b0, {1'b0, {1'b1, B[exp_base-1:0]}}};
                // $display("[DBG] saveMantissa: A=%b %b, B=%b %b", A[size-1], {1'b1, A[exp_base-1:0]}, B[size-1], {1'b1, B[exp_base-1:0]});
                // $display("[DBG] saveMantissa: signed_a=%b, signed_b=%b", signed_a, signed_b);
                next_mode <= Sshift;
            end

            Sshift: begin
                /**
                Shift register B left until exponent matches
                */
                if (A[size-2:exp_base] > B[size-2:exp_base]) begin
                    signed_b[exp_base:0] <= signed_b[exp_base:0] >> 1;
                    B[size-2:exp_base] <= B[size-2:exp_base] + 1;
                    // $display("[DBG] shift: shifted signed_b to %b", signed_b[exp_base-1:0]);
                    next_mode <= Sshift;                                    
                end else begin
                    // $display("[DBG] shift: exponent final value %b", B[size-2:exp_base]);
                    next_mode <= SadjustMagnitude;
                end
            end

            SadjustMagnitude: begin
                //! let the following happen only once
                if (A[size-1] == 1'b1) begin
                    signed_a <= ~signed_a + 1;
                    // $display("[DBG] adjustMagnitude: set inverted magnitude A");
                end
                if (B[size-1] == 1'b1) begin
                    signed_b <= ~signed_b + 1;
                    // $display("[DBG] adjustMagnitude: set inverted magnitude B");
                end
                next_mode <= Sadd;
            end

            Sadd: begin
                /**
                now exponents should match
                put them together
                */
                signed_c <= signed_a + signed_b;                    // this would lead to dropping of Cout
                // $display("signed_a=%b", signed_a);
                // $display("signed_b=%b", signed_b);
                // $display("signed_c=%b", signed_c);
                next_mode <= SbackToC;
            end

            SbackToC: begin
                C[size-1] <= signed_c[exp_base+2];                  // assign sign as the MSB
                C[size-2:exp_base] <= A[size-2:exp_base];           // assign exponent of any number
                // $display("[DBG] backToC: C=%b", C);
                next_mode <= SinvertMantissaC;
            end

            SinvertMantissaC: begin                                 // store the magnitude
                if (signed_c[exp_base+2] == 1'b1) begin
                    signed_c[exp_base+1:0] <= ~signed_c[exp_base+1:0] + 1; // signed_a storing intermediate 2's complement
                    // $display("[DBG] invertMantissaC: Inverting");
                end else begin
                    signed_c[exp_base+1:0] <= signed_c[exp_base+1:0];
                end
                next_mode <= SnormalizeC;
            end

            SnormalizeC: begin
                // ! running even when condition should be false
                if (signed_c[23+1] == 1'b1) begin
                    signed_c[exp_base+1:0] <= signed_c[exp_base+1:0] >> 1;
                    C[size-2:exp_base] <= C[size-2:exp_base] + 1;
                    // $display("[DBG] normalizeC: shift right signed_c=%b", signed_c);
                    next_mode <= next_mode;

                end else if (signed_c[exp_base] == 1'b0) begin                  // else shift right
                    signed_c[exp_base+1:0] <= signed_c[exp_base+1:0] << 1;
                    C[size-2:exp_base] <= C[size-2:exp_base] - 1;
                    // $display("[DBG] normalizeC: shift left signed_a=%b", signed_c);
                    next_mode <= next_mode;

                end else begin
                    C[exp_base-1:0] <= signed_c[exp_base-1:0];
                    // $display("[DBG] normalizeC: saved");
                    // $display("[DBG] normalizeC: signed_c=%b", signed_c);
                    next_mode <= SmantissaBackToC;
                end
            end

            SmantissaBackToC: begin
                C[exp_base-1:0] <= signed_c[exp_base-1:0];    
                next_mode <= Sstay;        
                done <= 1;
            end

            Sstay: begin
                // $display("[DBG] stay:");
                next_mode <= Sstay;
            end
            default: begin
                corrupt <= 1;
            end 
        endcase

    end

endmodule

CS220/Lab5/floating_point_addition_tb.v
`include "floating_point_addition.v"

module floating_point_addition_tb();

    parameter k = 32;
    reg [k-1:0] A;
    reg [k-1:0] B;
    reg clk, reset;
    wire [k-1:0] C;
    wire corrupt, done;

    always #5 clk <= ~clk;
    floating_point_addition #(k) uut(.a(A), .b(B), .clk(clk), .C(C), .corrupt(corrupt), .reset(reset), .done(done));

    initial begin
        $dumpfile("vcd/floating_point_addition_tb.vcd");
        $dumpvars(5, floating_point_addition_tb);
        clk <= 1'b0;
        reset <= 1'b0;
    end

    initial begin
        #20
        reset <= 1;
        A <= 32'b00111110111000000000000000000000;  // 0.4375
        B <= 32'b00111111000000000000000000000000;  // 0.5
        #10
        reset <= 0;
        #200
        $display("Final C: %b", C);
        
        #20
        reset <= 1;
        A <= 32'b11000000001000000000000000000000;  // -2.5
        B <= 32'b11000000011000000000000000000000;  // -3.5
        #10
        reset <= 0;
        #200
        $display("Final C: %b", C);

        #20
        reset <= 1;
        A <= 32'b01000011001010100100000000000000;  // 170.25
        B <= 32'b11000011011001011010000000000000;  // -229.625
        #10
        reset <= 0;
        #200
        $display("Final C: %b", C);
        $finish;
    end

endmodule

/*
works for positives
0 10000111 10001111111000000000000
0 10000111 10001111111000000000000

works for A=pos, B=neg
0 10000100 11011011000000000000000
0 10000100 11011011000000000000000
works for A=neg, B=pos
1 10000100 11011011000000000000000

-399.875
works for negatives
1 10000111 10001111111000000000000
1 10000111 10001111111000000000000
*/

CS220/Lab5/vcd/floating_point_addition_tb.vcd
$date
	Thu Mar  2 03:13:06 2023
$end
$version
	Icarus Verilog
$end
$timescale
	1s
$end
$scope module floating_point_addition_tb $end
$var wire 1 ! done $end
$var wire 1 " corrupt $end
$var wire 32 # C [31:0] $end
$var reg 32 $ A [31:0] $end
$var reg 32 % B [31:0] $end
$var reg 1 & clk $end
$var reg 1 ' reset $end
$scope module uut $end
$var wire 32 ( a [31:0] $end
$var wire 32 ) b [31:0] $end
$var wire 1 & clk $end
$var wire 1 ' reset $end
$var reg 32 * A [31:0] $end
$var reg 32 + B [31:0] $end
$var reg 32 , C [31:0] $end
$var reg 1 " corrupt $end
$var reg 1 ! done $end
$var reg 4 - mode [3:0] $end
$var reg 4 . next_mode [3:0] $end
$var reg 26 / signed_a [25:0] $end
$var reg 26 0 signed_b [25:0] $end
$var reg 26 1 signed_c [25:0] $end
$upscope $end
$upscope $end
$enddefinitions $end
#0
$dumpvars
bx 1
bx 0
bx /
b0 .
bx -
bx ,
bx +
bx *
bx )
bx (
0'
0&
bx %
bx $
bx #
1"
x!
$end
#5
b1 .
b0 -
1&
#10
b1 .
0&
#15
b10 .
b1 -
1&
#20
b111111000000000000000000000000 +
b111110111000000000000000000000 *
b1 .
0!
b0 -
0&
b111111000000000000000000000000 %
b111111000000000000000000000000 )
b111110111000000000000000000000 $
b111110111000000000000000000000 (
1'
#25
b1 .
1&
#30
b111110111000000000000000000000 +
b111111000000000000000000000000 *
b10 .
b1 -
0&
0'
#35
b111000000000000000000000 0
b100000000000000000000000 /
b11 .
b10 -
1&
#40
b11 .
0&
#45
b111111011000000000000000000000 +
b11100000000000000000000 0
b11 .
b11 -
1&
#50
b100 .
0&
#55
b101 .
b100 -
1&
#60
b101 .
0&
#65
b111100000000000000000000 1
b110 .
b101 -
1&
#70
b110 .
0&
#75
b1111110xxxxxxxxxxxxxxxxxxxxxxx #
b1111110xxxxxxxxxxxxxxxxxxxxxxx ,
b111 .
b110 -
1&
#80
b111 .
0&
#85
b1000 .
b111 -
1&
#90
b1000 .
0&
#95
b111111011100000000000000000000 #
b111111011100000000000000000000 ,
b1001 .
b1000 -
1&
#100
b1001 .
0&
#105
1!
b1010 .
b1001 -
1&
#110
b1010 .
0&
#115
b1010 .
b1010 -
1&
#120
b1010 .
0&
#125
b1010 .
1&
#130
b1010 .
0&
#135
b1010 .
1&
#140
b1010 .
0&
#145
b1010 .
1&
#150
b1010 .
0&
#155
b1010 .
1&
#160
b1010 .
0&
#165
b1010 .
1&
#170
b1010 .
0&
#175
b1010 .
1&
#180
b1010 .
0&
#185
b1010 .
1&
#190
b1010 .
0&
#195
b1010 .
1&
#200
b1010 .
0&
#205
b1010 .
1&
#210
b1010 .
0&
#215
b1010 .
1&
#220
b1010 .
0&
#225
b1010 .
1&
#230
b1010 .
0&
#235
b1010 .
1&
#240
b1010 .
0&
#245
b1010 .
1&
#250
b11000000011000000000000000000000 +
b11000000001000000000000000000000 *
b1 .
0!
b0 -
0&
b11000000011000000000000000000000 %
b11000000011000000000000000000000 )
b11000000001000000000000000000000 $
b11000000001000000000000000000000 (
1'
#255
b1 .
1&
#260
b10 .
b1 -
0&
0'
#265
b111000000000000000000000 0
b101000000000000000000000 /
b11 .
b10 -
1&
#270
b11 .
0&
#275
b100 .
b11 -
1&
#280
b100 .
0&
#285
b11001000000000000000000000 0
b11011000000000000000000000 /
b101 .
b100 -
1&
#290
b111000000000000000000000 0
b101000000000000000000000 /
b101 .
0&
#295
b10100000000000000000000000 1
b11001000000000000000000000 0
b11011000000000000000000000 /
b110 .
b101 -
1&
#300
b110 .
0&
#305
b11000000011100000000000000000000 #
b11000000011100000000000000000000 ,
b111 .
b110 -
1&
#310
b111 .
0&
#315
b11100000000000000000000000 1
b1000 .
b111 -
1&
#320
b10100000000000000000000000 1
b1000 .
0&
#325
b11000000111100000000000000000000 #
b11000000111100000000000000000000 ,
b10110000000000000000000000 1
b1000 .
b1000 -
1&
#330
b11000000110000000000000000000000 #
b11000000110000000000000000000000 ,
b1001 .
0&
#335
1!
b1010 .
b1001 -
1&
#340
b1010 .
0&
#345
b1010 .
b1010 -
1&
#350
b1010 .
0&
#355
b1010 .
1&
#360
b1010 .
0&
#365
b1010 .
1&
#370
b1010 .
0&
#375
b1010 .
1&
#380
b1010 .
0&
#385
b1010 .
1&
#390
b1010 .
0&
#395
b1010 .
1&
#400
b1010 .
0&
#405
b1010 .
1&
#410
b1010 .
0&
#415
b1010 .
1&
#420
b1010 .
0&
#425
b1010 .
1&
#430
b1010 .
0&
#435
b1010 .
1&
#440
b1010 .
0&
#445
b1010 .
1&
#450
b1010 .
0&
#455
b1010 .
1&
#460
b1010 .
0&
#465
b1010 .
1&
#470
b1010 .
0&
#475
b1010 .
1&
#480
b11000011011001011010000000000000 +
b1000011001010100100000000000000 *
b1 .
0!
b0 -
0&
b11000011011001011010000000000000 %
b11000011011001011010000000000000 )
b1000011001010100100000000000000 $
b1000011001010100100000000000000 (
1'
#485
b1 .
1&
#490
b10 .
b1 -
0&
0'
#495
b111001011010000000000000 0
b101010100100000000000000 /
b11 .
b10 -
1&
#500
b11 .
0&
#505
b100 .
b11 -
1&
#510
b100 .
0&
#515
b11000110100110000000000000 0
b101 .
b100 -
1&
#520
b111001011010000000000000 0
b101 .
0&
#525
b11110001001010000000000000 1
b11000110100110000000000000 0
b110 .
b101 -
1&
#530
b110 .
0&
#535
b11000011010000000000000000000000 #
b11000011010000000000000000000000 ,
b111 .
b110 -
1&
#540
b111 .
0&
#545
b10001110110110000000000000 1
b1000 .
b111 -
1&
#550
b11110001001010000000000000 1
b1000 .
0&
#555
b11000010110000000000000000000000 #
b11000010110000000000000000000000 ,
b10011101101100000000000000 1
b1000 .
b1000 -
1&
#560
b11000010010000000000000000000000 #
b11000010010000000000000000000000 ,
b10111011011000000000000000 1
b1000 .
0&
#565
b11000010011011011000000000000000 #
b11000010011011011000000000000000 ,
b1001 .
1&
#570
b1001 .
0&
#575
1!
b1010 .
b1001 -
1&
#580
b1010 .
0&
#585
b1010 .
b1010 -
1&
#590
b1010 .
0&
#595
b1010 .
1&
#600
b1010 .
0&
#605
b1010 .
1&
#610
b1010 .
0&
#615
b1010 .
1&
#620
b1010 .
0&
#625
b1010 .
1&
#630
b1010 .
0&
#635
b1010 .
1&
#640
b1010 .
0&
#645
b1010 .
1&
#650
b1010 .
0&
#655
b1010 .
1&
#660
b1010 .
0&
#665
b1010 .
1&
#670
b1010 .
0&
#675
b1010 .
1&
#680
b1010 .
0&
#685
b1010 .
1&
#690
b1010 .
0&
