CS220/Lab5/right_shift_register.v
module right_shift_register(
    in, out, clk
);
    parameter k = 8;

    input [k-1:0] in;
    output reg [k-1:0] out;
    input clk;

    always @(posedge clk) begin
        out <= in >> 1;
    end

endmodule

CS220/Lab5/left_shift_register.v
module left_shift_register(
    in, out, clk
);
    parameter k = 8;

    input [k-1:0] in;
    output reg [k-1:0] out;
    input clk;

    always @(posedge clk) begin
        // out[k-1:k-5] <= in[k-1:k-5] >> 1;
        // out[k-6:0] <= in[k-6:0] << 1;
        out <= in << 1;
    end

endmodule

CS220/Lab5/shift_register_tb.v
`include "left_shift_register.v"
`include "right_shift_register.v"

module shift_register_tb();

    parameter k = 8;
    reg [k-1:0] in;
    wire [k-1:0] out, out2;
    reg clk;

    left_shift_register #(k) lsr(.in(in), .out(out), .clk(clk));
    right_shift_register #(k) rsr(.in(in), .out(out2), .clk(clk));

    initial begin

        $dumpfile("vcd/shift_register_tb.vcd");
        $dumpvars(5, shift_register_tb);
        clk = 1'b0;
        $monitor("clk=%b, in=%b, out=%b, out2=%b", clk, in, out, out2);

    end

    always #5 clk <= ~clk;

    initial begin

        #10
        in <= $random;
        #10
        in <= out;
        #10
        in <= out;
        #10
        in <= out;
        #10
        in <= out;
        #10
        in <= out;
        #10
        in <= out;
        #10
        $finish;

    end


endmodule

CS220/Lab5/vcd/shift_register_tb.vcd
$date
	Sun Feb 26 22:27:03 2023
$end
$version
	Icarus Verilog
$end
$timescale
	1s
$end
$scope module shift_register_tb $end
$var wire 8 ! out2 [7:0] $end
$var wire 8 " out [7:0] $end
$var reg 1 # clk $end
$var reg 8 $ in [7:0] $end
$scope module lsr $end
$var wire 1 # clk $end
$var wire 8 % in [7:0] $end
$var reg 8 & out [7:0] $end
$upscope $end
$scope module rsr $end
$var wire 1 # clk $end
$var wire 8 ' in [7:0] $end
$var reg 8 ( out [7:0] $end
$upscope $end
$upscope $end
$enddefinitions $end
#0
$dumpvars
bx (
bx '
bx &
bx %
bx $
0#
bx "
bx !
$end
#5
b0xxxxxx0 "
b0xxxxxx0 &
b0xxxxxxx !
b0xxxxxxx (
1#
#10
0#
b100100 $
b100100 %
b100100 '
#15
b10010 !
b10010 (
b10000 "
b10000 &
1#
#20
0#
b10000 $
b10000 %
b10000 '
#25
b1000 "
b1000 &
b1000 !
b1000 (
1#
#30
0#
b1000 $
b1000 %
b1000 '
#35
b100 !
b100 (
b0 "
b0 &
1#
#40
0#
b0 $
b0 %
b0 '
#45
b0 !
b0 (
1#
