CS220/Lab3/drafts/counter.v
module TFF (CLK,T,OUT);
  input CLK,T;
  output reg OUT=0;
  always @ ( posedge CLK ) begin
    if(T) OUT<=~OUT;
    else  OUT<=OUT;
  end
endmodule // TFF

module NINE_YET (IN,OUT);
  input  [3:0] IN;
  output reg [1:0]OUT;
  always @ ( * ) begin
    if(IN==9) OUT<=2'b01; //Q[3] should be toggled the next cycle, Q[2] should not
    else OUT<={~IN[2],~IN[0]}; //just pass Q` of Tff[2] and Tff[0]
  end
endmodule // NINE_YET

module counter (CLK,OUT);
  input CLK;
  output [3:0] OUT;
  wire [1:0]nine_yet_op;
  NINE_YET m(OUT,nine_yet_op);

  TFF Q0(CLK,1'b1,OUT[0]);
  TFF Q1(nine_yet_op[0],1'b1,OUT[1]);
  TFF Q2(~OUT[1],1'b1,OUT[2]);
  TFF Q3(nine_yet_op[1],1'b1,OUT[3]);
endmodule // counter

CS220/Lab3/drafts/test.v
`include "counter.v"
`timescale 1ms/1ps

module counter_tb();

    wire [3:0] q;
    reg clk;
    integer i;
    counter counter(.OUT(q), .CLK(clk));

    initial begin
        $dumpfile("vcd/counter_tb.vcd");
        $dumpvars(5, counter_tb);
        #85
        #15;
        #40
        $finish;
	end

    initial begin
        $monitor("%b", q);
    end

	initial begin
		clk = 0;
		for(i = 0; i < 140; i = i + 1)
			#2 clk = ~clk;
	end

endmodule

CS220/Lab3/drafts/vcd/counter_tb.vcd
$date
	Tue Feb  7 02:17:52 2023
$end
$version
	Icarus Verilog
$end
$timescale
	1ps
$end
$scope module counter_tb $end
$var wire 4 ! q [3:0] $end
$var reg 1 " clk $end
$var integer 32 # i [31:0] $end
$scope module counter $end
$var wire 1 " CLK $end
$var wire 2 $ nine_yet_op [1:0] $end
$var wire 4 % OUT [3:0] $end
$scope module Q0 $end
$var wire 1 " CLK $end
$var wire 1 & T $end
$var reg 1 ' OUT $end
$upscope $end
$scope module Q1 $end
$var wire 1 ( CLK $end
$var wire 1 ) T $end
$var reg 1 * OUT $end
$upscope $end
$scope module Q2 $end
$var wire 1 + CLK $end
$var wire 1 , T $end
$var reg 1 - OUT $end
$upscope $end
$scope module Q3 $end
$var wire 1 . CLK $end
$var wire 1 / T $end
$var reg 1 0 OUT $end
$upscope $end
$scope module m $end
$var wire 4 1 IN [3:0] $end
$var reg 2 2 OUT [1:0] $end
$upscope $end
$upscope $end
$upscope $end
$enddefinitions $end
#0
$dumpvars
b1 2
b1110 1
10
1/
0.
1-
1,
0+
1*
1)
1(
0'
1&
b1110 %
b1 $
b0 #
0"
b1110 !
$end
#2000000000
0(
b0 $
b0 2
b1111 !
b1111 %
b1111 1
1'
b1 #
1"
#4000000000
b10 #
0"
#6000000000
00
1.
0-
1+
0*
1(
b11 $
b11 2
b0 !
b0 %
b0 1
0'
b11 #
1"
#8000000000
b100 #
0"
#10000000000
0(
b10 $
b10 2
b1 !
b1 %
b1 1
1'
b101 #
1"
#12000000000
b110 #
0"
#14000000000
0+
1*
1(
b11 $
b11 2
b10 !
b10 %
b10 1
0'
b111 #
1"
#16000000000
b1000 #
0"
#18000000000
0(
b10 $
b10 2
b11 !
b11 %
b11 1
1'
b1001 #
1"
#20000000000
b1010 #
0"
#22000000000
0.
1-
1+
0*
1(
b1 $
b1 2
b100 !
b100 %
b100 1
0'
b1011 #
1"
#24000000000
b1100 #
0"
#26000000000
0(
b0 $
b0 2
b101 !
b101 %
b101 1
1'
b1101 #
1"
#28000000000
b1110 #
0"
#30000000000
0+
1*
1(
b1 $
b1 2
b110 !
b110 %
b110 1
0'
b1111 #
1"
#32000000000
b10000 #
0"
#34000000000
0(
b0 $
b0 2
b111 !
b111 %
b111 1
1'
b10001 #
1"
#36000000000
b10010 #
0"
#38000000000
10
1.
0-
1+
0*
1(
b11 $
b11 2
b1000 !
b1000 %
b1000 1
0'
b10011 #
1"
#40000000000
b10100 #
0"
#42000000000
0.
b1 $
b1 2
b1001 !
b1001 %
b1001 1
1'
b10101 #
1"
#44000000000
b10110 #
0"
#46000000000
00
1.
b11 $
b11 2
b0 !
b0 %
b0 1
0'
b10111 #
1"
#48000000000
b11000 #
0"
#50000000000
0(
b10 $
b10 2
b1 !
b1 %
b1 1
1'
b11001 #
1"
#52000000000
b11010 #
0"
#54000000000
0+
1*
1(
b11 $
b11 2
b10 !
b10 %
b10 1
0'
b11011 #
1"
#56000000000
b11100 #
0"
#58000000000
0(
b10 $
b10 2
b11 !
b11 %
b11 1
1'
b11101 #
1"
#60000000000
b11110 #
0"
#62000000000
0.
1-
1+
0*
1(
b1 $
b1 2
b100 !
b100 %
b100 1
0'
b11111 #
1"
#64000000000
b100000 #
0"
#66000000000
0(
b0 $
b0 2
b101 !
b101 %
b101 1
1'
b100001 #
1"
#68000000000
b100010 #
0"
#70000000000
0+
1*
1(
b1 $
b1 2
b110 !
b110 %
b110 1
0'
b100011 #
1"
#72000000000
b100100 #
0"
#74000000000
0(
b0 $
b0 2
b111 !
b111 %
b111 1
1'
b100101 #
1"
#76000000000
b100110 #
0"
#78000000000
10
1.
0-
1+
0*
1(
b11 $
b11 2
b1000 !
b1000 %
b1000 1
0'
b100111 #
1"
#80000000000
b101000 #
0"
#82000000000
0.
b1 $
b1 2
b1001 !
b1001 %
b1001 1
1'
b101001 #
1"
#84000000000
b101010 #
0"
#86000000000
00
1.
b11 $
b11 2
b0 !
b0 %
b0 1
0'
b101011 #
1"
#88000000000
b101100 #
0"
#90000000000
0(
b10 $
b10 2
b1 !
b1 %
b1 1
1'
b101101 #
1"
#92000000000
b101110 #
0"
#94000000000
0+
1*
1(
b11 $
b11 2
b10 !
b10 %
b10 1
0'
b101111 #
1"
#96000000000
b110000 #
0"
#98000000000
0(
b10 $
b10 2
b11 !
b11 %
b11 1
1'
b110001 #
1"
#100000000000
b110010 #
0"
#102000000000
0.
1-
1+
0*
1(
b1 $
b1 2
b100 !
b100 %
b100 1
0'
b110011 #
1"
#104000000000
b110100 #
0"
#106000000000
0(
b0 $
b0 2
b101 !
b101 %
b101 1
1'
b110101 #
1"
#108000000000
b110110 #
0"
#110000000000
0+
1*
1(
b1 $
b1 2
b110 !
b110 %
b110 1
0'
b110111 #
1"
#112000000000
b111000 #
0"
#114000000000
0(
b0 $
b0 2
b111 !
b111 %
b111 1
1'
b111001 #
1"
#116000000000
b111010 #
0"
#118000000000
10
1.
0-
1+
0*
1(
b11 $
b11 2
b1000 !
b1000 %
b1000 1
0'
b111011 #
1"
#120000000000
b111100 #
0"
#122000000000
0.
b1 $
b1 2
b1001 !
b1001 %
b1001 1
1'
b111101 #
1"
#124000000000
b111110 #
0"
#126000000000
00
1.
b11 $
b11 2
b0 !
b0 %
b0 1
0'
b111111 #
1"
#128000000000
b1000000 #
0"
#130000000000
0(
b10 $
b10 2
b1 !
b1 %
b1 1
1'
b1000001 #
1"
#132000000000
b1000010 #
0"
#134000000000
0+
1*
1(
b11 $
b11 2
b10 !
b10 %
b10 1
0'
b1000011 #
1"
#136000000000
b1000100 #
0"
#138000000000
0(
b10 $
b10 2
b11 !
b11 %
b11 1
1'
b1000101 #
1"
#140000000000
b1000110 #
0"
