CS220/Lab4/delay_one_cycle.v
module delay_one_cycle(
    input clk,
    input[31:0] original_signal,
    output reg[31:0] delayed_signal
);

    always @(posedge clk) begin
        delayed_signal <= original_signal;
    end

endmodule

CS220/Lab4/mod_veda.v
`include "delay_one_cycle.v"

module mod_veda(
    input clk,
    input rst,
    input write_enable,
    input [4:0] addr_a,
    input [4:0] addr_b,
    input [31:0] datain,
    input mode,
    output [31:0] dataout
);

    integer i;
    reg [31:0] cells[31:0]; // first signifies data bits, second is number of such cells

    reg [31:0] out;
    delay_one_cycle delay(.clk(clk), .original_signal(out), .delayed_signal(dataout));

    initial begin

        out <= 0;
        for (i = 0; i < 32; i = i + 1)
            cells[i] <= 0;

    end

    always @(posedge clk) begin
        if (rst == 1) begin

            for (i = 0; i < 32; i = i + 1) begin : reset
                cells[i] <= 0;
            end
            
        end
        if (write_enable) begin

            cells[addr_a] = datain;
            out = cells[addr_b];

        end else if (mode == 1) begin

            out = cells[addr_b];
            
        end
    end

endmodule

CS220/Lab4/mod_veda_tb.v
`include "mod_veda.v"
`timescale 1ns / 1ps

module mod_veda_tb();

    reg clk;
    reg [4:0] addr_a;
    reg [4:0] addr_b;
    reg [31:0] datain;
    reg rst;
    reg write_enable;
    reg mode;
    wire [31:0] dataout;

    mod_veda v(
        .clk(clk),
        .rst(rst),
        .write_enable(write_enable),
        .addr_a(addr_a),
        .addr_b(addr_b),
        .datain(datain),
        .mode(mode),
        .dataout(dataout)
    );

    always #5 clk = ~ clk;

    initial begin
        write_enable = 1;
        mode = 0;
        addr_a = 4'hc;
        addr_b = 4'ha;
        datain = 55;
        #20
        mode = 0;
        addr_a = 4'ha;
        addr_b = 4'hd;
        datain = 56;
        #20
        mode = 1;
        addr_a = 4'h2;
        addr_b = 4'hc;
        #20
        mode = 1;
        addr_a = 4'hc;
        addr_b = 4'ha;
        datain = 55;
        #20
        mode = 0;
        addr_a = 4'ha;
        addr_b = 4'hd;
        datain = 56;
        #20
        mode = 1;
        addr_a = 4'h2;
        addr_b = 4'ha;
        #20
        $finish;
    end

    initial begin
        $dumpfile("vcd/mod_veda_tb.vcd");
        $dumpvars(5, mod_veda_tb);
        clk = 1'b0;
    end

    initial begin

        $monitor("rst=%b mode=%b addr_a=%d, addr_b=%d datain=%d \t dataout=%d", rst, mode, addr_a, addr_b, datain, dataout);
        rst = 1'b1;
        #5 rst = 1'b0;
        
    end

endmodule

CS220/Lab4/vcd/mod_veda_tb.vcd
$date
	Wed Feb 15 13:50:04 2023
$end
$version
	Icarus Verilog
$end
$timescale
	1ps
$end
$scope module mod_veda_tb $end
$var wire 32 ! dataout [31:0] $end
$var reg 5 " addr_a [4:0] $end
$var reg 5 # addr_b [4:0] $end
$var reg 1 $ clk $end
$var reg 32 % datain [31:0] $end
$var reg 1 & mode $end
$var reg 1 ' rst $end
$var reg 1 ( write_enable $end
$scope module v $end
$var wire 5 ) addr_a [4:0] $end
$var wire 5 * addr_b [4:0] $end
$var wire 1 $ clk $end
$var wire 32 + datain [31:0] $end
$var wire 1 & mode $end
$var wire 1 ' rst $end
$var wire 1 ( write_enable $end
$var wire 32 , dataout [31:0] $end
$var reg 32 - out [31:0] $end
$var integer 32 . i [31:0] $end
$scope module delay $end
$var wire 1 $ clk $end
$var wire 32 / original_signal [31:0] $end
$var reg 32 0 delayed_signal [31:0] $end
$upscope $end
$scope begin reset $end
$upscope $end
$upscope $end
$upscope $end
$enddefinitions $end
#0
$dumpvars
bx 0
b0 /
b100000 .
b0 -
bx ,
b110111 +
b1010 *
b1100 )
1(
1'
0&
b110111 %
0$
b1010 #
b1100 "
bx !
$end
#5000
b0 !
b0 ,
b0 0
0'
1$
#10000
0$
#15000
1$
#20000
0$
b111000 %
b111000 +
b1101 #
b1101 *
b1010 "
b1010 )
#25000
1$
#30000
0$
#35000
1$
#40000
0$
b1100 #
b1100 *
b10 "
b10 )
1&
#45000
b110111 !
b110111 ,
b110111 0
b110111 -
b110111 /
1$
#50000
0$
#55000
1$
#60000
0$
b110111 %
b110111 +
b1010 #
b1010 *
b1100 "
b1100 )
#65000
b111000 !
b111000 ,
b111000 0
b111000 -
b111000 /
1$
#70000
0$
#75000
1$
#80000
0$
b111000 %
b111000 +
b1101 #
b1101 *
b1010 "
b1010 )
0&
#85000
b0 !
b0 ,
b0 0
b0 -
b0 /
1$
#90000
0$
#95000
1$
#100000
0$
b1010 #
b1010 *
b10 "
b10 )
1&
#105000
b111000 !
b111000 ,
b111000 0
b111000 -
b111000 /
1$
