CS220/Lab4/delay_one_cycle.v
module delay_one_cycle(
    input clk,
    input[31:0] original_signal,
    output reg[31:0] delayed_signal
);

    always @(posedge clk) begin
        delayed_signal <= original_signal;
    end

endmodule

CS220/Lab4/veda.v
`include "delay_one_cycle.v"

module veda(
    input clk,
    input rst,
    input write_enable,
    input [4:0] addr,
    input [31:0] datain,
    input mode,
    output [31:0] dataout
);

    integer i;
    reg [31:0] cells[31:0]; // first signifies data bits, second is number of such cells
    reg [31:0] out;
    // delay_one_cycle delay(.clk(clk), .original_signal(out), .delayed_signal(dataout));
    assign dataout = out;

    initial begin

        out <= 0;
        for (i = 0; i < 32; i = i + 1)
            cells[i] <= 0;

    end

    always @(posedge clk) begin
        if (rst == 1) begin

            for (i = 0; i < 32; i = i + 1) begin : reset
                cells[i] <= 0;
            end
            
        end else begin
            if (write_enable && mode == 0) begin : scribble

                cells[addr] <= datain;
                out <= datain;

            end else if (write_enable && mode == 1) begin : interpret

                cells[addr] <= datain;
                out <= cells[addr];
                
            end else begin

                out <= cells[addr];

            end
        end
    end

endmodule

CS220/Lab4/veda_tb.v
`include "veda.v"
`timescale 1ns / 1ps

module veda_tb();

    reg clk;
    reg [4:0] addr;
    reg [31:0] datain;
    reg rst;
    reg write_enable;
    reg mode;
    wire [31:0] dataout;

    veda v(
        .clk(clk),
        .rst(rst),
        .write_enable(write_enable),
        .addr(addr),
        .datain(datain),
        .mode(mode),
        .dataout(dataout)
    );

    always #5 clk = ~ clk;

    initial begin
        write_enable = 1;
        mode = 0;
        addr = 4'ha;
        datain = 2000;
        #20
        mode = 0;
        addr = 4'hd;
        datain = 3000;
        #20
        mode = 1;
        addr = 4'hc;
        datain = 3000;
        #20
        mode = 1;
        addr = 4'ha;
        datain = 4000;
        #20
        mode = 0;
        addr = 4'hd;
        datain = 56;
        #20
        mode = 1;
        addr = 4'ha;
        datain = 5000;
        #20
        $finish;
    end

    initial begin
        $dumpfile("vcd/veda_tb.vcd");
        $dumpvars(3, veda_tb);
        clk = 1'b0;
    end

    initial begin

        $monitor("rst=%b mode=%b addr=%d datain=%d \t dataout=%d", rst, mode, addr, datain, dataout);
        rst = 1'b1;
        #5 rst = 1'b0;
        
    end

endmodule

CS220/Lab4/vcd/veda_tb.vcd
$date
	Sun Feb 26 15:36:39 2023
$end
$version
	Icarus Verilog
$end
$timescale
	1ps
$end
$scope module veda_tb $end
$var wire 32 ! dataout [31:0] $end
$var reg 5 " addr [4:0] $end
$var reg 1 # clk $end
$var reg 32 $ datain [31:0] $end
$var reg 1 % mode $end
$var reg 1 & rst $end
$var reg 1 ' write_enable $end
$scope module v $end
$var wire 5 ( addr [4:0] $end
$var wire 1 # clk $end
$var wire 32 ) datain [31:0] $end
$var wire 32 * dataout [31:0] $end
$var wire 1 % mode $end
$var wire 1 & rst $end
$var wire 1 ' write_enable $end
$var reg 32 + out [31:0] $end
$var integer 32 , i [31:0] $end
$scope begin interpret $end
$upscope $end
$scope begin reset $end
$upscope $end
$scope begin scribble $end
$upscope $end
$upscope $end
$upscope $end
$enddefinitions $end
#0
$dumpvars
b100000 ,
b0 +
b0 *
b11111010000 )
b1010 (
1'
1&
0%
b11111010000 $
0#
b1010 "
b0 !
$end
#5000
b11111010000 !
b11111010000 *
b11111010000 +
0&
1#
#10000
0#
#15000
1#
#20000
0#
b101110111000 $
b101110111000 )
b1101 "
b1101 (
#25000
b101110111000 !
b101110111000 *
b101110111000 +
1#
#30000
0#
#35000
1#
#40000
0#
b1100 "
b1100 (
1%
#45000
b0 !
b0 *
b0 +
1#
#50000
0#
#55000
b101110111000 !
b101110111000 *
b101110111000 +
1#
#60000
0#
b111110100000 $
b111110100000 )
b1010 "
b1010 (
#65000
b11111010000 !
b11111010000 *
b11111010000 +
1#
#70000
0#
#75000
b111110100000 !
b111110100000 *
b111110100000 +
1#
#80000
0#
b111000 $
b111000 )
b1101 "
b1101 (
0%
#85000
b111000 !
b111000 *
b111000 +
1#
#90000
0#
#95000
1#
#100000
0#
b1001110001000 $
b1001110001000 )
b1010 "
b1010 (
1%
#105000
b111110100000 !
b111110100000 *
b111110100000 +
1#
#110000
0#
#115000
b1001110001000 !
b1001110001000 *
b1001110001000 +
1#
